pysumma/__init__.py
pysumma/_version.py
pysumma/decisions.py
pysumma/distributed.py
pysumma/ensemble.py
pysumma/evaluation.py
pysumma/file_manager.py
pysumma/force_file_list.py
pysumma/global_params.py
pysumma/gui.py
pysumma/hydroshare_utils.py
pysumma/option.py
pysumma/output_control.py
pysumma/preprocess_csv.py
pysumma/simulation.py
pysumma/spatial_params.py
pysumma/utils.py
pysumma/calibration/__init__.py
pysumma/calibration/ostrich.py
pysumma/calibration/meta/model_executable.template
pysumma/calibration/meta/ostIn.template
pysumma/calibration/meta/save_parameters.template
pysumma/hydroshare/__init__.py
pysumma/hydroshare/compat.py
pysumma/hydroshare/hydroshare.py
pysumma/hydroshare/progress.py
pysumma/hydroshare/resource.py
pysumma/hydroshare/threads.py
pysumma/hydroshare/utilities.py
pysumma/meta/__init__.py
pysumma/meta/decisions.json
pysumma/meta/file_manager.json
pysumma/meta/var_lookup.f90
pysumma/plotting/__init__.py
pysumma/plotting/energy_balance.py
pysumma/plotting/energybalance.py
pysumma/plotting/hovmoller.py
pysumma/plotting/layers.py
pysumma/plotting/plot.py
pysumma/plotting/plotting.py
pysumma/plotting/spatial.py
pysumma/plotting/timeseries.py
pysumma/plotting/utils.py
pysumma/plotting/water_balance.py
pysumma/plotting/waterbalance.py
pysumma/specworker/__init__.py
pysumma/specworker/compat.py
pysumma/specworker/jobs.py
pysumma/specworker/progress.py
pysumma/specworker/run_tasks.py
pysumma/specworker/tasks.py
pysumma/specworker/worker.py
pysumma/tests/__init__.py
pysumma/tests/test_pysumma.py
pysumma-3.0.3.dist-info/LICENSE
pysumma-3.0.3.dist-info/METADATA
pysumma-3.0.3.dist-info/WHEEL
pysumma-3.0.3.dist-info/top_level.txt
pysumma-3.0.3.dist-info/RECORD
